[{"type":"Real estate companies","amount":16150,"before_after":"before"},{"type":"Property developers","amount":8450,"before_after":"before"},{"type":"PACs","amount":8250,"before_after":"before"},{"type":"Small donors","amount":57047,"before_after":"before"},{"type":"Real estate companies","amount":7750,"before_after":"after"},{"type":"Property developers","amount":5650,"before_after":"after"},{"type":"PACs","amount":6200,"before_after":"after"},{"type":"Small donors","amount":399329,"before_after":"after"}]