[{"type":"Political candidates","amount":47205,"before_after":"before"},{"type":"Property developers","amount":51100,"before_after":"before"},{"type":"PACs","amount":16500,"before_after":"before"},{"type":"Small donors","amount":25400,"before_after":"before"},{"type":"Political candidates","amount":12400,"before_after":"after"},{"type":"Property developers","amount":36500,"before_after":"after"},{"type":"PACs","amount":7750,"before_after":"after"},{"type":"Small donors","amount":177800,"before_after":"after"}]